pacote_testpy_dio/__init__.py
pacote_testpy_dio/hello.py
pacote_testpy_dio-0.0.2.dist-info/METADATA
pacote_testpy_dio-0.0.2.dist-info/WHEEL
pacote_testpy_dio-0.0.2.dist-info/top_level.txt
pacote_testpy_dio-0.0.2.dist-info/RECORD
