Metadata-Version: 2.4
Name: pacote_testpy_dio
Version: 0.0.2
Summary: Frase simples para progressão de aprendizado
Home-page: https://github.com/Douglas-A-M/simple-package-template
Author: Douglas
Author-email: douglasalvesmoreira2013@gmail.com
Requires-Python: >=3.8
Dynamic: author
Dynamic: author-email
Dynamic: description
Dynamic: description-content-type
Dynamic: home-page
Dynamic: requires-python
Dynamic: summary
